[
  {"word": "Agua", "number": "01"},
  {"word": "Perro", "number": "14"},
  {"word": "Dinero", "number": "32"},
  {"word": "Muerte", "number": "08"},
  {"word": "Bebé", "number": "02"},
  {"word": "Boda", "number": "90"},
  {"word": "Culebra", "number": "48"},
  {"word": "Pescado", "number": "25"},
  {"word": "Caballo", "number": "15"},
  {"word": "Gato", "number": "04"},
  {"word": "Casa", "number": "46"},
  {"word": "Carro", "number": "81"},
  {"word": "Sangre", "number": "18"},
  {"word": "Zapatos", "number": "39"},
  {"word": "Dientes", "number": "51"},
  {"word": "Embarazo", "number": "89"},
  {"word": "Lluvia", "number": "11"},
  {"word": "Policia", "number": "77"},
  {"word": "Fuego", "number": "03"},
  {"word": "Oro", "number": "55"},
  {"word": "Avion", "number": "60"},
  {"word": "Caca", "number": "71"},
  {"word": "Excremento", "number": "71"},
  {"word": "Ratas", "number": "19"},
  {"word": "Piojos", "number": "22"},
  {"word": "Araña", "number": "33"},
  {"word": "Sapo", "number": "70"},
  {"word": "Monos", "number": "93"},
  {"word": "Mar", "number": "01"},
  {"word": "Plata", "number": "32"},
  {"word": "Amor", "number": "05"},
  {"word": "Llanto", "number": "64"},
  {"word": "Pelea", "number": "80"}
]
